mynotification/__init__.py
mynotification/notification_android.py
mynotification/notification_desktop.py
mynotification-1.0.7.dist-info/LICENSE
mynotification-1.0.7.dist-info/METADATA
mynotification-1.0.7.dist-info/WHEEL
mynotification-1.0.7.dist-info/RECORD
