Metadata-Version: 2.3
Name: mynotification
Version: 1.0.7
Summary: Just a simple library to send desktopnotifications
Author: tct123
Author-email: 42028373+tct123@users.noreply.github.com
Requires-Python: >=3.9
Classifier: Programming Language :: Python :: 3
Classifier: Programming Language :: Python :: 3.9
Classifier: Programming Language :: Python :: 3.10
Classifier: Programming Language :: Python :: 3.11
Classifier: Programming Language :: Python :: 3.12
Classifier: Programming Language :: Python :: 3.13
